turbojpeg.cpython-37m-x86_64-linux-gnu.so
turbojpeg-0.0.2.dist-info/WHEEL
turbojpeg-0.0.2.dist-info/top_level.txt
turbojpeg-0.0.2.dist-info/RECORD
turbojpeg-0.0.2.dist-info/METADATA
turbojpeg.libs/libgcc_s-a3a07607.so.1
turbojpeg.libs/libturbojpeg-d24f7ddd.so.0.3.0
turbojpeg.libs/libstdc++-496613c0.so.6.0.32
