Metadata-Version: 2.1
Name: turbojpeg
Version: 0.0.2
Summary: Python bindungs for libjpeg-turbo using pybind11
Home-page: https://github.com/Dobatymo/turbojpeg-python
Author: Dobatymo
Author-email: Dobatymo@users.noreply.github.com
Requires-Python: >=3.7
Provides-Extra: test
Requires-Dist: Pillow ; extra == 'test'
Requires-Dist: numpy ; extra == 'test'
Requires-Dist: scikit-image ; extra == 'test'
